shidal/__init__.py
shidal/daemon.py
shidal-1.0.9.dist-info/LICENSE
shidal-1.0.9.dist-info/METADATA
shidal-1.0.9.dist-info/WHEEL
shidal-1.0.9.dist-info/top_level.txt
shidal-1.0.9.dist-info/RECORD
