Metadata-Version: 2.1
Name: shidal
Version: 1.0.9
Summary: Simple hid action listener
Home-page: UNKNOWN
Author: dataniklas
Author-email: 51879435+data-niklas@users.noreply.github.com
License: UNKNOWN
Platform: UNKNOWN
Requires-Dist: hid
